rtctools_heat_network/__init__.py
rtctools_heat_network/_darcy_weisbach.py
rtctools_heat_network/_heat_loss_u_values_pipe.py
rtctools_heat_network/_version.py
rtctools_heat_network/asset_sizing_mixin.py
rtctools_heat_network/base_component_type_mixin.py
rtctools_heat_network/component_type_mixin.py
rtctools_heat_network/constants.py
rtctools_heat_network/control_variables.py
rtctools_heat_network/demand_insulation_class.py
rtctools_heat_network/electricity_physics_mixin.py
rtctools_heat_network/financial_mixin.py
rtctools_heat_network/gas_physics_mixin.py
rtctools_heat_network/head_loss_class.py
rtctools_heat_network/heat_network_common.py
rtctools_heat_network/heat_physics_mixin.py
rtctools_heat_network/physics_mixin.py
rtctools_heat_network/pipe_class.py
rtctools_heat_network/techno_economic_mixin.py
rtctools_heat_network/topology.py
rtctools_heat_network/esdl/__init__.py
rtctools_heat_network/esdl/_edr_pipes.json
rtctools_heat_network/esdl/_exceptions.py
rtctools_heat_network/esdl/_update_edr_pipes_json.py
rtctools_heat_network/esdl/asset_to_component_base.py
rtctools_heat_network/esdl/common.py
rtctools_heat_network/esdl/edr_pipe_class.py
rtctools_heat_network/esdl/esdl_heat_model.py
rtctools_heat_network/esdl/esdl_mixin.py
rtctools_heat_network/esdl/esdl_model_base.py
rtctools_heat_network/esdl/esdl_qth_model.py
rtctools_heat_network/influxdb/__init__.py
rtctools_heat_network/influxdb/profile.py
rtctools_heat_network/modelica/WarmingUp/package.mo
rtctools_heat_network/modelica/WarmingUp/HeatNetwork/package.mo
rtctools_heat_network/modelica/WarmingUp/HeatNetwork/Heat/Buffer.mo
rtctools_heat_network/modelica/WarmingUp/HeatNetwork/Heat/CheckValve.mo
rtctools_heat_network/modelica/WarmingUp/HeatNetwork/Heat/ControlValve.mo
rtctools_heat_network/modelica/WarmingUp/HeatNetwork/Heat/Demand.mo
rtctools_heat_network/modelica/WarmingUp/HeatNetwork/Heat/GeothermalSource.mo
rtctools_heat_network/modelica/WarmingUp/HeatNetwork/Heat/HeatPort.mo
rtc_tools_heat_network-0.4.6.dist-info/COPYING.LESSER
rtc_tools_heat_network-0.4.6.dist-info/METADATA
rtc_tools_heat_network-0.4.6.dist-info/WHEEL
rtc_tools_heat_network-0.4.6.dist-info/entry_points.txt
rtc_tools_heat_network-0.4.6.dist-info/top_level.txt
rtc_tools_heat_network-0.4.6.dist-info/RECORD
