Metadata-Version: 2.1
Name: rtc-tools-heat-network
Version: 0.4.6
Summary: Heat network models for RTC-Tools 2.
Home-page: https://github.com/Nieuwe-Warmte-Nu/rtc-tools-heat-network
Author: Jim Rojer
Author-email: jim.rojer@tno.nl
Maintainer: Jim Rojer, Kobus van Rooyen, Kelbij Star, Femke Janssen, Jesús Andrés Rodríguez Sarasty, Thijs van der Klauw
License: LGPLv3
Keywords: heat network optimization rtc tools
Platform: Windows
Platform: Linux
Platform: Mac OS-X
Platform: Unix
Classifier: Development Status :: 4 - Beta
Classifier: Intended Audience :: Science/Research
Classifier: Intended Audience :: Information Technology
Classifier: License :: OSI Approved :: GNU Lesser General Public License v3 (LGPLv3)
Classifier: Programming Language :: Other
Classifier: Topic :: Scientific/Engineering :: GIS
Classifier: Topic :: Scientific/Engineering :: Mathematics
Classifier: Topic :: Scientific/Engineering :: Physics
Classifier: Operating System :: Microsoft :: Windows
Classifier: Operating System :: POSIX
Classifier: Operating System :: Unix
Classifier: Operating System :: MacOS
Requires-Python: >=3.8,<3.11
License-File: COPYING.LESSER
Requires-Dist: influxdb >=5.3.1
Requires-Dist: pyecore
Requires-Dist: pymoca >=0.9.0
Requires-Dist: rtc-tools ==2.6.0a3
Requires-Dist: pyesdl >=23.12
Requires-Dist: pandas <2.0,>=1.3.1
Requires-Dist: casadi ==3.6.3
